AutoTrade/__init__.py
AutoTrade/audio/__init__.py
AutoTrade/video/__init__.py
test/__init__.py
AutoTrade-2023.9.1.dist-info/LICENSE.txt
AutoTrade-2023.9.1.dist-info/METADATA
AutoTrade-2023.9.1.dist-info/WHEEL
AutoTrade-2023.9.1.dist-info/top_level.txt
AutoTrade-2023.9.1.dist-info/RECORD
